s3/__init__.py
s3/dumper.py
s3/exceptions.py
s3/logger.py
s3_downloader-1.0.0.dist-info/LICENSE
s3_downloader-1.0.0.dist-info/METADATA
s3_downloader-1.0.0.dist-info/WHEEL
s3_downloader-1.0.0.dist-info/top_level.txt
s3_downloader-1.0.0.dist-info/RECORD
