Metadata-Version: 2.1
Name: s3-downloader
Version: 1.0.0
Summary: Python module to download objects in an S3 bucket.
Author-email: Vignesh Rao <svignesh1793@gmail.com>
License: MIT License
Project-URL: Homepage, https://github.com/thevickypedia/s3-downloader
Project-URL: Docs, https://thevickypedia.github.io/s3-downloader/
Project-URL: Source, https://github.com/thevickypedia/s3-downloader
Project-URL: Bug Tracker, https://github.com/thevickypedia/s3-downloader/issues
Keywords: s3
Classifier: Development Status :: 1 - Planning
Classifier: Intended Audience :: Information Technology
Classifier: Operating System :: OS Independent
Classifier: License :: OSI Approved :: MIT License
Classifier: Programming Language :: Python :: 3.9
Classifier: Topic :: Internet :: File Transfer Protocol (FTP)
Requires-Python: >=3.8
License-File: LICENSE
Requires-Dist: boto3
Requires-Dist: tqdm
Provides-Extra: dev
Requires-Dist: sphinx ==5.1.1 ; extra == 'dev'
Requires-Dist: pre-commit ; extra == 'dev'
Requires-Dist: recommonmark ; extra == 'dev'
